[{"adcode":"110106001","name":"右安门街道","level":"street","parent":"110106"},{"adcode":"110106002","name":"太平桥街道","level":"street","parent":"110106"},{"adcode":"110106003","name":"西罗园街道","level":"street","parent":"110106"},{"adcode":"110106004","name":"大红门街道","level":"street","parent":"110106"},{"adcode":"110106006","name":"东高地街道","level":"street","parent":"110106"},{"adcode":"110106007","name":"东铁匠营街道","level":"street","parent":"110106"},{"adcode":"110106009","name":"丰台街道","level":"street","parent":"110106"},{"adcode":"110106012","name":"云岗街道","level":"street","parent":"110106"},{"adcode":"110106013","name":"方庄(地区)街道","level":"street","parent":"110106"},{"adcode":"110106014","name":"宛平城(地区)街道","level":"street","parent":"110106"},{"adcode":"110106015","name":"马家堡街道","level":"street","parent":"110106"},{"adcode":"110106016","name":"和义街道","level":"street","parent":"110106"},{"adcode":"110106100","name":"长辛店镇","level":"street","parent":"110106"},{"adcode":"110106101","name":"王佐镇","level":"street","parent":"110106"},{"adcode":"110106201","name":"卢沟桥(地区)乡","level":"street","parent":"110106"},{"adcode":"110106202","name":"花乡(地区)乡","level":"street","parent":"110106"},{"adcode":"110106203","name":"南苑(地区)乡","level":"street","parent":"110106"}]