[{"adcode":"130183100","name":"晋州镇","level":"street","parent":"130183"},{"adcode":"130183101","name":"总十庄镇","level":"street","parent":"130183"},{"adcode":"130183102","name":"营里镇","level":"street","parent":"130183"},{"adcode":"130183103","name":"桃园镇","level":"street","parent":"130183"},{"adcode":"130183104","name":"东卓宿镇","level":"street","parent":"130183"},{"adcode":"130183105","name":"马于镇","level":"street","parent":"130183"},{"adcode":"130183106","name":"小樵镇","level":"street","parent":"130183"},{"adcode":"130183107","name":"槐树镇","level":"street","parent":"130183"},{"adcode":"130183108","name":"东里庄镇","level":"street","parent":"130183"},{"adcode":"130183201","name":"周家庄乡","level":"street","parent":"130183"}]