[{"adcode":"130535100","name":"临西镇","level":"street","parent":"130535"},{"adcode":"130535101","name":"河西镇","level":"street","parent":"130535"},{"adcode":"130535102","name":"下堡寺镇","level":"street","parent":"130535"},{"adcode":"130535103","name":"尖冢镇","level":"street","parent":"130535"},{"adcode":"130535104","name":"老官寨镇","level":"street","parent":"130535"},{"adcode":"130535105","name":"吕寨镇","level":"street","parent":"130535"},{"adcode":"130535200","name":"东枣园乡","level":"street","parent":"130535"},{"adcode":"130535203","name":"摇鞍镇乡","level":"street","parent":"130535"},{"adcode":"130535204","name":"大刘庄乡","level":"street","parent":"130535"}]