[{"adcode":"130608100","name":"清苑镇","level":"street","parent":"130608"},{"adcode":"130608101","name":"冉庄镇","level":"street","parent":"130608"},{"adcode":"130608102","name":"阳城镇","level":"street","parent":"130608"},{"adcode":"130608103","name":"魏村镇","level":"street","parent":"130608"},{"adcode":"130608104","name":"温仁镇","level":"street","parent":"130608"},{"adcode":"130608105","name":"张登镇","level":"street","parent":"130608"},{"adcode":"130608106","name":"大庄镇","level":"street","parent":"130608"},{"adcode":"130608107","name":"臧村镇","level":"street","parent":"130608"},{"adcode":"130608108","name":"望亭镇","level":"street","parent":"130608"},{"adcode":"130608200","name":"白团乡","level":"street","parent":"130608"},{"adcode":"130608201","name":"北店乡","level":"street","parent":"130608"},{"adcode":"130608202","name":"石桥乡","level":"street","parent":"130608"},{"adcode":"130608203","name":"李庄乡","level":"street","parent":"130608"},{"adcode":"130608204","name":"北王力乡","level":"street","parent":"130608"},{"adcode":"130608205","name":"东闾乡","level":"street","parent":"130608"},{"adcode":"130608206","name":"何桥乡","level":"street","parent":"130608"},{"adcode":"130608207","name":"孙村乡","level":"street","parent":"130608"},{"adcode":"130608208","name":"阎庄乡","level":"street","parent":"130608"}]