[{"adcode":"140928100","name":"砚城镇","level":"street","parent":"140928"},{"adcode":"140928101","name":"小河头镇","level":"street","parent":"140928"},{"adcode":"140928102","name":"三岔镇","level":"street","parent":"140928"},{"adcode":"140928200","name":"前所乡","level":"street","parent":"140928"},{"adcode":"140928201","name":"李家坪乡","level":"street","parent":"140928"},{"adcode":"140928202","name":"孙家坪乡","level":"street","parent":"140928"},{"adcode":"140928203","name":"梁家坪乡","level":"street","parent":"140928"},{"adcode":"140928204","name":"胡会乡","level":"street","parent":"140928"},{"adcode":"140928205","name":"新寨乡","level":"street","parent":"140928"},{"adcode":"140928206","name":"韩家楼乡","level":"street","parent":"140928"},{"adcode":"140928207","name":"东秀庄乡","level":"street","parent":"140928"},{"adcode":"140928208","name":"杏岭子乡","level":"street","parent":"140928"}]