[{"adcode":"141031100","name":"龙泉镇","level":"street","parent":"141031"},{"adcode":"141031101","name":"午城镇","level":"street","parent":"141031"},{"adcode":"141031102","name":"黄土镇","level":"street","parent":"141031"},{"adcode":"141031200","name":"阳头升乡","level":"street","parent":"141031"},{"adcode":"141031201","name":"寨子乡","level":"street","parent":"141031"},{"adcode":"141031202","name":"陡坡乡","level":"street","parent":"141031"},{"adcode":"141031203","name":"下李乡","level":"street","parent":"141031"},{"adcode":"141031204","name":"城南乡","level":"street","parent":"141031"}]