[{"adcode":"210802001","name":"八田地街道","level":"street","parent":"210802"},{"adcode":"210802002","name":"建丰街道","level":"street","parent":"210802"},{"adcode":"210802003","name":"建设街道","level":"street","parent":"210802"},{"adcode":"210802004","name":"跃进街道","level":"street","parent":"210802"},{"adcode":"210802005","name":"东风街道","level":"street","parent":"210802"},{"adcode":"210802006","name":"新兴街道","level":"street","parent":"210802"},{"adcode":"210802007","name":"新建街道","level":"street","parent":"210802"}]