[{"adcode":"220421100","name":"东丰镇","level":"street","parent":"220421"},{"adcode":"220421101","name":"大阳镇","level":"street","parent":"220421"},{"adcode":"220421102","name":"横道河镇","level":"street","parent":"220421"},{"adcode":"220421103","name":"那丹伯镇","level":"street","parent":"220421"},{"adcode":"220421104","name":"猴石镇","level":"street","parent":"220421"},{"adcode":"220421105","name":"杨木林镇","level":"street","parent":"220421"},{"adcode":"220421106","name":"小四平镇","level":"street","parent":"220421"},{"adcode":"220421107","name":"黄河镇","level":"street","parent":"220421"},{"adcode":"220421108","name":"拉拉河镇","level":"street","parent":"220421"},{"adcode":"220421109","name":"沙河镇","level":"street","parent":"220421"},{"adcode":"220421110","name":"南屯基镇","level":"street","parent":"220421"},{"adcode":"220421111","name":"大兴镇","level":"street","parent":"220421"},{"adcode":"220421201","name":"三合满族朝鲜族乡","level":"street","parent":"220421"},{"adcode":"220421207","name":"二龙山乡","level":"street","parent":"220421"}]