[{"adcode":"231085100","name":"八面通镇","level":"street","parent":"231085"},{"adcode":"231085101","name":"穆棱镇","level":"street","parent":"231085"},{"adcode":"231085102","name":"下城子镇","level":"street","parent":"231085"},{"adcode":"231085103","name":"马桥河镇","level":"street","parent":"231085"},{"adcode":"231085104","name":"兴源镇","level":"street","parent":"231085"},{"adcode":"231085105","name":"河西镇","level":"street","parent":"231085"},{"adcode":"231085200","name":"福禄朝鲜族满族乡","level":"street","parent":"231085"},{"adcode":"231085202","name":"共和乡","level":"street","parent":"231085"}]