[{"adcode":"310116001","name":"石化街道","level":"street","parent":"310116"},{"adcode":"310116101","name":"朱泾镇","level":"street","parent":"310116"},{"adcode":"310116102","name":"枫泾镇","level":"street","parent":"310116"},{"adcode":"310116103","name":"张堰镇","level":"street","parent":"310116"},{"adcode":"310116104","name":"亭林镇","level":"street","parent":"310116"},{"adcode":"310116105","name":"吕巷镇","level":"street","parent":"310116"},{"adcode":"310116107","name":"廊下镇","level":"street","parent":"310116"},{"adcode":"310116109","name":"金山卫镇","level":"street","parent":"310116"},{"adcode":"310116112","name":"漕泾镇","level":"street","parent":"310116"},{"adcode":"310116113","name":"山阳镇","level":"street","parent":"310116"}]