[{"adcode":"330881001","name":"双塔街道","level":"street","parent":"330881"},{"adcode":"330881002","name":"虎山街道","level":"street","parent":"330881"},{"adcode":"330881003","name":"清湖街道","level":"street","parent":"330881"},{"adcode":"330881102","name":"上余镇","level":"street","parent":"330881"},{"adcode":"330881103","name":"贺村镇","level":"street","parent":"330881"},{"adcode":"330881105","name":"坛石镇","level":"street","parent":"330881"},{"adcode":"330881106","name":"大桥镇","level":"street","parent":"330881"},{"adcode":"330881107","name":"四都镇","level":"street","parent":"330881"},{"adcode":"330881109","name":"新塘边镇","level":"street","parent":"330881"},{"adcode":"330881110","name":"凤林镇","level":"street","parent":"330881"},{"adcode":"330881111","name":"峡口镇","level":"street","parent":"330881"},{"adcode":"330881112","name":"廿八都镇","level":"street","parent":"330881"},{"adcode":"330881113","name":"长台镇","level":"street","parent":"330881"},{"adcode":"330881114","name":"石门镇","level":"street","parent":"330881"},{"adcode":"330881200","name":"大陈乡","level":"street","parent":"330881"},{"adcode":"330881201","name":"碗窑乡","level":"street","parent":"330881"},{"adcode":"330881202","name":"保安乡","level":"street","parent":"330881"},{"adcode":"330881204","name":"张村乡","level":"street","parent":"330881"},{"adcode":"330881205","name":"塘源口乡","level":"street","parent":"330881"}]