[{"adcode":"340421100","name":"城关镇","level":"street","parent":"340421"},{"adcode":"340421102","name":"新集镇","level":"street","parent":"340421"},{"adcode":"340421103","name":"朱马店镇","level":"street","parent":"340421"},{"adcode":"340421104","name":"岳张集镇","level":"street","parent":"340421"},{"adcode":"340421106","name":"顾桥镇","level":"street","parent":"340421"},{"adcode":"340421107","name":"桂集镇","level":"street","parent":"340421"},{"adcode":"340421108","name":"凤凰镇","level":"street","parent":"340421"},{"adcode":"340421109","name":"杨村镇","level":"street","parent":"340421"},{"adcode":"340421111","name":"刘集镇","level":"street","parent":"340421"},{"adcode":"340421112","name":"大兴镇","level":"street","parent":"340421"},{"adcode":"340421113","name":"尚塘镇","level":"street","parent":"340421"},{"adcode":"340421114","name":"毛集镇","level":"street","parent":"340421"},{"adcode":"340421115","name":"夏集镇","level":"street","parent":"340421"},{"adcode":"340421116","name":"焦岗湖镇","level":"street","parent":"340421"},{"adcode":"340421205","name":"古店乡","level":"street","parent":"340421"},{"adcode":"340421206","name":"钱庙乡","level":"street","parent":"340421"},{"adcode":"340421210","name":"关店乡","level":"street","parent":"340421"},{"adcode":"340421212","name":"李冲回族乡","level":"street","parent":"340421"},{"adcode":"6067999","name":"丁集镇","level":"street","parent":"340421"}]