[{"adcode":"350721001","name":"双溪街道","level":"street","parent":"350721"},{"adcode":"350721101","name":"建西镇","level":"street","parent":"350721"},{"adcode":"350721102","name":"洋口镇","level":"street","parent":"350721"},{"adcode":"350721103","name":"元坑镇","level":"street","parent":"350721"},{"adcode":"350721105","name":"埔上镇","level":"street","parent":"350721"},{"adcode":"350721106","name":"大历镇","level":"street","parent":"350721"},{"adcode":"350721107","name":"大干镇","level":"street","parent":"350721"},{"adcode":"350721108","name":"仁寿镇","level":"street","parent":"350721"},{"adcode":"350721109","name":"郑坊镇","level":"street","parent":"350721"},{"adcode":"350721200","name":"洋墩乡","level":"street","parent":"350721"},{"adcode":"350721203","name":"岚下乡","level":"street","parent":"350721"},{"adcode":"350721204","name":"高阳乡","level":"street","parent":"350721"}]