[{"adcode":"350823100","name":"临江镇","level":"street","parent":"350823"},{"adcode":"350823101","name":"临城镇","level":"street","parent":"350823"},{"adcode":"350823102","name":"中都镇","level":"street","parent":"350823"},{"adcode":"350823103","name":"蓝溪镇","level":"street","parent":"350823"},{"adcode":"350823104","name":"稔田镇","level":"street","parent":"350823"},{"adcode":"350823105","name":"白砂镇","level":"street","parent":"350823"},{"adcode":"350823106","name":"古田镇","level":"street","parent":"350823"},{"adcode":"350823107","name":"才溪镇","level":"street","parent":"350823"},{"adcode":"350823108","name":"南阳镇","level":"street","parent":"350823"},{"adcode":"350823109","name":"蛟洋镇","level":"street","parent":"350823"},{"adcode":"350823110","name":"旧县镇","level":"street","parent":"350823"},{"adcode":"350823111","name":"溪口镇","level":"street","parent":"350823"},{"adcode":"350823112","name":"湖洋镇","level":"street","parent":"350823"},{"adcode":"350823113","name":"太拔镇","level":"street","parent":"350823"},{"adcode":"350823114","name":"通贤镇","level":"street","parent":"350823"},{"adcode":"350823115","name":"下都镇","level":"street","parent":"350823"},{"adcode":"350823116","name":"茶地镇","level":"street","parent":"350823"},{"adcode":"350823202","name":"庐丰畲族乡","level":"street","parent":"350823"},{"adcode":"350823206","name":"泮境乡","level":"street","parent":"350823"},{"adcode":"350823208","name":"步云乡","level":"street","parent":"350823"},{"adcode":"350823211","name":"官庄畲族乡","level":"street","parent":"350823"},{"adcode":"350823212","name":"珊瑚乡","level":"street","parent":"350823"}]