[{"adcode":"360733100","name":"文武坝镇","level":"street","parent":"360733"},{"adcode":"360733101","name":"筠门岭镇","level":"street","parent":"360733"},{"adcode":"360733102","name":"西江镇","level":"street","parent":"360733"},{"adcode":"360733103","name":"周田镇","level":"street","parent":"360733"},{"adcode":"360733104","name":"麻州镇","level":"street","parent":"360733"},{"adcode":"360733105","name":"庄口镇","level":"street","parent":"360733"},{"adcode":"360733201","name":"清溪乡","level":"street","parent":"360733"},{"adcode":"360733202","name":"右水乡","level":"street","parent":"360733"},{"adcode":"360733203","name":"高排乡","level":"street","parent":"360733"},{"adcode":"360733204","name":"晓龙乡","level":"street","parent":"360733"},{"adcode":"360733205","name":"珠兰乡","level":"street","parent":"360733"},{"adcode":"360733206","name":"洞头乡","level":"street","parent":"360733"},{"adcode":"360733207","name":"中村乡","level":"street","parent":"360733"},{"adcode":"360733208","name":"站塘乡","level":"street","parent":"360733"},{"adcode":"360733209","name":"永隆乡","level":"street","parent":"360733"},{"adcode":"360733210","name":"富城乡","level":"street","parent":"360733"},{"adcode":"360733211","name":"小密乡","level":"street","parent":"360733"},{"adcode":"360733213","name":"庄埠乡","level":"street","parent":"360733"},{"adcode":"360733214","name":"白鹅乡","level":"street","parent":"360733"},{"adcode":"360733400","name":"会昌县燕子窝工业园","level":"street","parent":"360733"}]