[{"adcode":"370404001","name":"坛山街道","level":"street","parent":"370404"},{"adcode":"370404002","name":"吴林街道","level":"street","parent":"370404"},{"adcode":"370404100","name":"古邵镇","level":"street","parent":"370404"},{"adcode":"370404101","name":"阴平镇","level":"street","parent":"370404"},{"adcode":"370404102","name":"底阁镇","level":"street","parent":"370404"},{"adcode":"370404103","name":"榴园镇","level":"street","parent":"370404"},{"adcode":"370404104","name":"峨山镇","level":"street","parent":"370404"}]