[{"adcode":"370613001","name":"黄海路街道","level":"street","parent":"370613"},{"adcode":"370613002","name":"初家街道","level":"street","parent":"370613"},{"adcode":"370613003","name":"滨海路街道","level":"street","parent":"370613"},{"adcode":"370613004","name":"院格庄街道","level":"street","parent":"370613"},{"adcode":"370613005","name":"解甲庄街道","level":"street","parent":"370613"},{"adcode":"370613006","name":"莱山街道","level":"street","parent":"370613"},{"adcode":"370613007","name":"马山街道","level":"street","parent":"370613"}]