[{"adcode":"371422001","name":"宁城街道","level":"street","parent":"371422"},{"adcode":"371422002","name":"津城街道","level":"street","parent":"371422"},{"adcode":"371422101","name":"柴胡店镇","level":"street","parent":"371422"},{"adcode":"371422102","name":"长官镇","level":"street","parent":"371422"},{"adcode":"371422103","name":"杜集镇","level":"street","parent":"371422"},{"adcode":"371422104","name":"保店镇","level":"street","parent":"371422"},{"adcode":"371422105","name":"大柳镇","level":"street","parent":"371422"},{"adcode":"371422106","name":"大曹镇","level":"street","parent":"371422"},{"adcode":"371422107","name":"相衙镇","level":"street","parent":"371422"},{"adcode":"371422108","name":"时集镇","level":"street","parent":"371422"},{"adcode":"371422109","name":"张大庄镇","level":"street","parent":"371422"},{"adcode":"371422201","name":"刘营伍乡","level":"street","parent":"371422"}]