[{"adcode":"371681001","name":"黛溪街道","level":"street","parent":"371681"},{"adcode":"371681002","name":"黄山街道","level":"street","parent":"371681"},{"adcode":"371681003","name":"高新街道","level":"street","parent":"371681"},{"adcode":"371681004","name":"好生街道","level":"street","parent":"371681"},{"adcode":"371681005","name":"西董街道","level":"street","parent":"371681"},{"adcode":"371681101","name":"长山镇","level":"street","parent":"371681"},{"adcode":"371681102","name":"魏桥镇","level":"street","parent":"371681"},{"adcode":"371681105","name":"临池镇","level":"street","parent":"371681"},{"adcode":"371681108","name":"焦桥镇","level":"street","parent":"371681"},{"adcode":"371681109","name":"韩店镇","level":"street","parent":"371681"},{"adcode":"371681110","name":"孙镇","level":"street","parent":"371681"},{"adcode":"371681111","name":"九户镇","level":"street","parent":"371681"},{"adcode":"371681112","name":"青阳镇","level":"street","parent":"371681"},{"adcode":"371681113","name":"明集镇","level":"street","parent":"371681"},{"adcode":"371681114","name":"台子镇","level":"street","parent":"371681"},{"adcode":"371681115","name":"码头镇","level":"street","parent":"371681"}]