[{"adcode":"410503001","name":"红旗路街道","level":"street","parent":"410503"},{"adcode":"410503003","name":"解放路街道","level":"street","parent":"410503"},{"adcode":"410503004","name":"灯塔路街道","level":"street","parent":"410503"},{"adcode":"410503005","name":"豆腐营街道","level":"street","parent":"410503"},{"adcode":"410503006","name":"洹北街道","level":"street","parent":"410503"},{"adcode":"410503011","name":"曙光街道","level":"street","parent":"410503"},{"adcode":"410503012","name":"民航街道","level":"street","parent":"410503"},{"adcode":"410503013","name":"彰东街道","level":"street","parent":"410503"},{"adcode":"410503014","name":"彰北街道","level":"street","parent":"410503"},{"adcode":"410503100","name":"柏庄镇","level":"street","parent":"410503"}]