[{"adcode":"410725100","name":"城关镇","level":"street","parent":"410725"},{"adcode":"410725102","name":"师寨镇","level":"street","parent":"410725"},{"adcode":"410725103","name":"齐街镇","level":"street","parent":"410725"},{"adcode":"410725104","name":"太平镇","level":"street","parent":"410725"},{"adcode":"410725105","name":"福宁集镇","level":"street","parent":"410725"},{"adcode":"410725106","name":"韩董庄镇","level":"street","parent":"410725"},{"adcode":"410725107","name":"原武镇","level":"street","parent":"410725"},{"adcode":"410725200","name":"葛埠口乡","level":"street","parent":"410725"},{"adcode":"410725206","name":"蒋庄乡","level":"street","parent":"410725"},{"adcode":"410725207","name":"官厂镇","level":"street","parent":"410725"},{"adcode":"410725209","name":"大宾镇","level":"street","parent":"410725"},{"adcode":"410725211","name":"陡门乡","level":"street","parent":"410725"},{"adcode":"410725215","name":"路寨乡","level":"street","parent":"410725"},{"adcode":"410725216","name":"阳阿乡","level":"street","parent":"410725"},{"adcode":"410725218","name":"靳堂乡","level":"street","parent":"410725"},{"adcode":"410725219","name":"祝楼乡","level":"street","parent":"410725"},{"adcode":"410725220","name":"桥北乡","level":"street","parent":"410725"}]