[{"adcode":"410882001","name":"覃怀街道","level":"street","parent":"410882"},{"adcode":"410882002","name":"怀庆街道","level":"street","parent":"410882"},{"adcode":"410882003","name":"太行街道","level":"street","parent":"410882"},{"adcode":"410882004","name":"沁园街道","level":"street","parent":"410882"},{"adcode":"410882100","name":"崇义镇","level":"street","parent":"410882"},{"adcode":"410882101","name":"西向镇","level":"street","parent":"410882"},{"adcode":"410882102","name":"西万镇","level":"street","parent":"410882"},{"adcode":"410882103","name":"柏香镇","level":"street","parent":"410882"},{"adcode":"410882104","name":"山王庄镇","level":"street","parent":"410882"},{"adcode":"410882105","name":"紫陵镇","level":"street","parent":"410882"},{"adcode":"410882200","name":"常平乡","level":"street","parent":"410882"},{"adcode":"410882201","name":"王召乡","level":"street","parent":"410882"},{"adcode":"410882205","name":"王曲乡","level":"street","parent":"410882"}]