[{"adcode":"411202001","name":"湖滨街道","level":"street","parent":"411202"},{"adcode":"411202002","name":"前进街道","level":"street","parent":"411202"},{"adcode":"411202003","name":"车站街道","level":"street","parent":"411202"},{"adcode":"411202004","name":"涧河街道","level":"street","parent":"411202"},{"adcode":"411202005","name":"大安街道","level":"street","parent":"411202"},{"adcode":"411202201","name":"交口乡","level":"street","parent":"411202"},{"adcode":"411202202","name":"磁钟乡","level":"street","parent":"411202"},{"adcode":"411202203","name":"高庙乡","level":"street","parent":"411202"},{"adcode":"411202400","name":"河南三门峡经济开发区","level":"street","parent":"411202"}]