[{"adcode":"430482001","name":"泉峰街道","level":"street","parent":"430482"},{"adcode":"430482002","name":"培元街道","level":"street","parent":"430482"},{"adcode":"430482003","name":"宜阳街道","level":"street","parent":"430482"},{"adcode":"430482101","name":"柏坊镇","level":"street","parent":"430482"},{"adcode":"430482103","name":"烟洲镇","level":"street","parent":"430482"},{"adcode":"430482104","name":"荫田镇","level":"street","parent":"430482"},{"adcode":"430482105","name":"白沙镇","level":"street","parent":"430482"},{"adcode":"430482106","name":"西岭镇","level":"street","parent":"430482"},{"adcode":"430482108","name":"三角塘镇","level":"street","parent":"430482"},{"adcode":"430482109","name":"洋泉镇","level":"street","parent":"430482"},{"adcode":"430482110","name":"庙前镇","level":"street","parent":"430482"},{"adcode":"430482111","name":"罗桥镇","level":"street","parent":"430482"},{"adcode":"430482112","name":"板桥镇","level":"street","parent":"430482"}]{"adcode":"430482113","name":"胜桥镇","level":"street","parent":"430482"},{"adcode":"430482114","name":"官岭镇","level":"street","parent":"430482"},{"adcode":"430482115","name":"新河镇","level":"street","parent":"430482"},{"adcode":"430482116","name":"水口山镇","level":"street","parent":"430482"},{"adcode":"430482201","name":"蓬塘乡","level":"street","parent":"430482"},{"adcode":"430482202","name":"兰江乡","level":"street","parent":"430482"},{"adcode":"430482203","name":"大堡乡","level":"street","parent":"430482"},{"adcode":"430482206","name":"塔山瑶族乡","level":"street","parent":"430482"}]