[{"adcode":"440117001","name":"街口街道","level":"street","parent":"440117"},{"adcode":"440117002","name":"城郊街道","level":"street","parent":"440117"},{"adcode":"440117003","name":"江埔街道","level":"street","parent":"440117"},{"adcode":"440117100","name":"温泉镇","level":"street","parent":"440117"},{"adcode":"440117101","name":"良口镇","level":"street","parent":"440117"},{"adcode":"440117102","name":"吕田镇","level":"street","parent":"440117"},{"adcode":"440117103","name":"太平镇","level":"street","parent":"440117"},{"adcode":"440117104","name":"鳌头镇","level":"street","parent":"440117"}]