[{"adcode":"450225100","name":"融水镇","level":"street","parent":"450225"},{"adcode":"450225101","name":"和睦镇","level":"street","parent":"450225"},{"adcode":"450225102","name":"三防镇","level":"street","parent":"450225"},{"adcode":"450225103","name":"怀宝镇","level":"street","parent":"450225"},{"adcode":"450225104","name":"洞头镇","level":"street","parent":"450225"},{"adcode":"450225105","name":"大浪镇","level":"street","parent":"450225"},{"adcode":"450225106","name":"永乐镇","level":"street","parent":"450225"},{"adcode":"450225202","name":"四荣乡","level":"street","parent":"450225"},{"adcode":"450225203","name":"香粉乡","level":"street","parent":"450225"},{"adcode":"450225204","name":"安太乡","level":"street","parent":"450225"},{"adcode":"450225206","name":"汪洞乡","level":"street","parent":"450225"},{"adcode":"450225207","name":"同练瑶族乡","level":"street","parent":"450225"},{"adcode":"450225208","name":"滚贝侗族乡","level":"street","parent":"450225"},{"adcode":"450225209","name":"杆洞乡","level":"street","parent":"450225"},{"adcode":"450225210","name":"安陲乡","level":"street","parent":"450225"},{"adcode":"450225212","name":"白云乡","level":"street","parent":"450225"},{"adcode":"450225213","name":"红水乡","level":"street","parent":"450225"},{"adcode":"450225214","name":"拱洞乡","level":"street","parent":"450225"},{"adcode":"450225215","name":"良寨乡","level":"street","parent":"450225"},{"adcode":"450225216","name":"大年乡","level":"street","parent":"450225"}]