[{"adcode":"460107001","name":"国兴街道","level":"street","parent":"460107"},{"adcode":"460107002","name":"府城街道","level":"street","parent":"460107"},{"adcode":"460107003","name":"滨江街道","level":"street","parent":"460107"},{"adcode":"460107004","name":"凤翔街道","level":"street","parent":"460107"},{"adcode":"460107101","name":"龙塘镇","level":"street","parent":"460107"},{"adcode":"460107102","name":"云龙镇","level":"street","parent":"460107"},{"adcode":"460107103","name":"红旗镇","level":"street","parent":"460107"},{"adcode":"460107104","name":"三门坡镇","level":"street","parent":"460107"},{"adcode":"460107105","name":"大坡镇","level":"street","parent":"460107"},{"adcode":"460107106","name":"甲子镇","level":"street","parent":"460107"},{"adcode":"460107107","name":"旧州镇","level":"street","parent":"460107"}]