[{"adcode":"510129001","name":"晋原街道","level":"street","parent":"510129"},{"adcode":"510129101","name":"王泗镇","level":"street","parent":"510129"},{"adcode":"510129103","name":"新场镇","level":"street","parent":"510129"},{"adcode":"510129104","name":"悦来镇","level":"street","parent":"510129"},{"adcode":"510129105","name":"安仁镇","level":"street","parent":"510129"},{"adcode":"510129106","name":"出阝江镇","level":"street","parent":"510129"},{"adcode":"510129108","name":"西岭镇","level":"street","parent":"510129"},{"adcode":"510129109","name":"斜源镇","level":"street","parent":"510129"},{"adcode":"510129110","name":"董场镇","level":"street","parent":"510129"},{"adcode":"510129111","name":"韩场镇","level":"street","parent":"510129"},{"adcode":"510129112","name":"三岔镇","level":"street","parent":"510129"},{"adcode":"510129113","name":"上安镇","level":"street","parent":"510129"},{"adcode":"510129114","name":"苏家镇","level":"street","parent":"510129"},{"adcode":"510129115","name":"青霞镇","level":"street","parent":"510129"},{"adcode":"510129116","name":"沙渠镇","level":"street","parent":"510129"},{"adcode":"510129117","name":"蔡场镇","level":"street","parent":"510129"},{"adcode":"510129118","name":"花水湾镇","level":"street","parent":"510129"},{"adcode":"510129202","name":"雾山乡","level":"street","parent":"510129"},{"adcode":"510129203","name":"金星乡","level":"street","parent":"510129"},{"adcode":"510129205","name":"鹤鸣乡","level":"street","parent":"510129"}]