[{"adcode":"513422100","name":"乔瓦镇","level":"street","parent":"513422"},{"adcode":"513422101","name":"瓦厂镇","level":"street","parent":"513422"},{"adcode":"513422102","name":"茶布朗镇","level":"street","parent":"513422"},{"adcode":"513422103","name":"雅砻江镇","level":"street","parent":"513422"},{"adcode":"513422201","name":"博科乡","level":"street","parent":"513422"},{"adcode":"513422202","name":"宁朗乡","level":"street","parent":"513422"},{"adcode":"513422203","name":"依吉乡","level":"street","parent":"513422"},{"adcode":"513422204","name":"俄亚纳西族乡","level":"street","parent":"513422"},{"adcode":"513422205","name":"水洛乡","level":"street","parent":"513422"},{"adcode":"513422206","name":"牦牛坪乡","level":"street","parent":"513422"},{"adcode":"513422207","name":"屋脚蒙古族乡","level":"street","parent":"513422"},{"adcode":"513422208","name":"项脚蒙古族乡","level":"street","parent":"513422"},{"adcode":"513422209","name":"李子坪乡","level":"street","parent":"513422"},{"adcode":"513422210","name":"列瓦乡","level":"street","parent":"513422"},{"adcode":"513422211","name":"芽祖乡","level":"street","parent":"513422"},{"adcode":"513422212","name":"下麦地乡","level":"street","parent":"513422"},{"adcode":"513422213","name":"西秋乡","level":"street","parent":"513422"},{"adcode":"513422214","name":"克尔乡","level":"street","parent":"513422"},{"adcode":"513422215","name":"白碉苗族乡","level":"street","parent":"513422"},{"adcode":"513422216","name":"三桷垭乡","level":"street","parent":"513422"},{"adcode":"513422217","name":"倮波乡","level":"street","parent":"513422"},{"adcode":"513422218","name":"卡拉乡","level":"street","parent":"513422"},{"adcode":"513422219","name":"后所乡","level":"street","parent":"513422"},{"adcode":"513422220","name":"沙湾乡","level":"street","parent":"513422"},{"adcode":"513422222","name":"固增苗族乡","level":"street","parent":"513422"},{"adcode":"513422223","name":"麦日乡","level":"street","parent":"513422"},{"adcode":"513422224","name":"东朗乡","level":"street","parent":"513422"},{"adcode":"513422225","name":"唐央乡","level":"street","parent":"513422"},{"adcode":"513422226","name":"博窝乡","level":"street","parent":"513422"}]