[{"adcode":"513401001","name":"西城街道","level":"street","parent":"513401"},{"adcode":"513401002","name":"东城街道","level":"street","parent":"513401"},{"adcode":"513401003","name":"北城街道","level":"street","parent":"513401"},{"adcode":"513401004","name":"长安街道","level":"street","parent":"513401"},{"adcode":"513401005","name":"新村街道","level":"street","parent":"513401"},{"adcode":"513401006","name":"长宁街道","level":"street","parent":"513401"},{"adcode":"513401100","name":"马道镇","level":"street","parent":"513401"},{"adcode":"513401101","name":"礼州镇","level":"street","parent":"513401"},{"adcode":"513401102","name":"安宁镇","level":"street","parent":"513401"},{"adcode":"513401103","name":"川兴镇","level":"street","parent":"513401"},{"adcode":"513401104","name":"黄联关镇","level":"street","parent":"513401"},{"adcode":"513401105","name":"佑君镇","level":"street","parent":"513401"},{"adcode":"513401106","name":"太和镇","level":"street","parent":"513401"},{"adcode":"513401107","name":"安哈镇","level":"street","parent":"513401"},{"adcode":"513401200","name":"西郊乡","level":"street","parent":"513401"},{"adcode":"513401201","name":"高枧乡","level":"street","parent":"513401"},{"adcode":"513401202","name":"小庙乡","level":"street","parent":"513401"},{"adcode":"513401203","name":"四合乡","level":"street","parent":"513401"},{"adcode":"513401204","name":"月华乡","level":"street","parent":"513401"},{"adcode":"513401205","name":"兴胜乡","level":"street","parent":"513401"},{"adcode":"513401206","name":"琅环乡","level":"street","parent":"513401"},{"adcode":"513401207","name":"民胜乡","level":"street","parent":"513401"},{"adcode":"513401208","name":"西乡乡","level":"street","parent":"513401"},{"adcode":"513401209","name":"樟木箐乡","level":"street","parent":"513401"},{"adcode":"513401210","name":"响水乡","level":"street","parent":"513401"},{"adcode":"513401211","name":"开元乡","level":"street","parent":"513401"},{"adcode":"513401212","name":"大兴乡","level":"street","parent":"513401"},{"adcode":"513401213","name":"海南乡","level":"street","parent":"513401"},{"adcode":"513401214","name":"大箐乡","level":"street","parent":"513401"},{"adcode":"513401215","name":"经久乡","level":"street","parent":"513401"},{"adcode":"513401216","name":"西溪乡","level":"street","parent":"513401"},{"adcode":"513401217","name":"黄水乡","level":"street","parent":"513401"},{"adcode":"513401218","name":"洛古波乡","level":"street","parent":"513401"},{"adcode":"513401219","name":"裕隆回族乡","level":"street","parent":"513401"},{"adcode":"513401220","name":"高草回族乡","level":"street","parent":"513401"},{"adcode":"513401221","name":"中坝乡","level":"street","parent":"513401"},{"adcode":"513401222","name":"阿七乡","level":"street","parent":"513401"},{"adcode":"513401223","name":"荞地乡","level":"street","parent":"513401"},{"adcode":"513401224","name":"磨盘乡","level":"street","parent":"513401"},{"adcode":"513401225","name":"巴汝乡","level":"street","parent":"513401"},{"adcode":"513401226","name":"银厂乡","level":"street","parent":"513401"},{"adcode":"513401227","name":"白马乡","level":"street","parent":"513401"},{"adcode":"513401228","name":"马鞍山乡","level":"street","parent":"513401"}]