[{"adcode":"520111101","name":"青岩镇","level":"street","parent":"520111"},{"adcode":"520111102","name":"石板镇","level":"street","parent":"520111"},{"adcode":"520111103","name":"党武镇","level":"street","parent":"520111"},{"adcode":"520111104","name":"麦坪镇","level":"street","parent":"520111"},{"adcode":"520111105","name":"燕楼镇","level":"street","parent":"520111"},{"adcode":"520111201","name":"孟关苗族布依族乡","level":"street","parent":"520111"},{"adcode":"520111204","name":"湖潮苗族布依族乡","level":"street","parent":"520111"},{"adcode":"520111205","name":"久安乡","level":"street","parent":"520111"},{"adcode":"520111207","name":"高坡苗族乡","level":"street","parent":"520111"},{"adcode":"520111208","name":"黔陶布依族苗族乡","level":"street","parent":"520111"},{"adcode":"520111209","name":"马铃布依族苗族乡","level":"street","parent":"520111"},{"adcode":"520111402","name":"贵筑社区","level":"street","parent":"520111"},{"adcode":"520111403","name":"溪北社区","level":"street","parent":"520111"},{"adcode":"520111404","name":"清溪社区","level":"street","parent":"520111"},{"adcode":"520111410","name":"平桥社区","level":"street","parent":"520111"},{"adcode":"520111414","name":"黄河社区","level":"street","parent":"520111"},{"adcode":"520111415","name":"三江社区","level":"street","parent":"520111"},{"adcode":"520111417","name":"金竹社区","level":"street","parent":"520111"},{"adcode":"12531999","name":"长江街道","level":"street","parent":"520111"}]