[{"adcode":"522701006","name":"文峰街道","level":"street","parent":"522701"},{"adcode":"522701007","name":"广惠街道","level":"street","parent":"522701"},{"adcode":"522701008","name":"小围寨街道","level":"street","parent":"522701"},{"adcode":"522701009","name":"沙包堡街道","level":"street","parent":"522701"},{"adcode":"522701010","name":"绿茵湖街道","level":"street","parent":"522701"},{"adcode":"522701108","name":"墨冲镇","level":"street","parent":"522701"},{"adcode":"522701109","name":"平浪镇","level":"street","parent":"522701"},{"adcode":"522701112","name":"毛尖镇","level":"street","parent":"522701"},{"adcode":"522701113","name":"匀东镇","level":"street","parent":"522701"},{"adcode":"522701208","name":"归兰水族乡","level":"street","parent":"522701"}]