[{"adcode":"610430001","name":"城关街道","level":"street","parent":"610430"},{"adcode":"610430101","name":"官庄镇","level":"street","parent":"610430"},{"adcode":"610430103","name":"方里镇","level":"street","parent":"610430"},{"adcode":"610430104","name":"润镇","level":"street","parent":"610430"},{"adcode":"610430105","name":"车坞镇","level":"street","parent":"610430"},{"adcode":"610430106","name":"铁王镇","level":"street","parent":"610430"},{"adcode":"610430107","name":"石桥镇","level":"street","parent":"610430"},{"adcode":"610430109","name":"十里塬镇","level":"street","parent":"610430"}]