[{"adcode":"610723001","name":"洋州街道","level":"street","parent":"610723"},{"adcode":"610723002","name":"戚氏街道","level":"street","parent":"610723"},{"adcode":"610723003","name":"纸坊街道","level":"street","parent":"610723"},{"adcode":"610723103","name":"龙亭镇","level":"street","parent":"610723"},{"adcode":"610723104","name":"谢村镇","level":"street","parent":"610723"},{"adcode":"610723105","name":"马畅镇","level":"street","parent":"610723"},{"adcode":"610723107","name":"溢水镇","level":"street","parent":"610723"},{"adcode":"610723108","name":"磨子桥镇","level":"street","parent":"610723"},{"adcode":"610723109","name":"黄家营镇","level":"street","parent":"610723"},{"adcode":"610723110","name":"黄安镇","level":"street","parent":"610723"},{"adcode":"610723111","name":"黄金峡镇","level":"street","parent":"610723"},{"adcode":"610723112","name":"槐树关镇","level":"street","parent":"610723"},{"adcode":"610723113","name":"金水镇","level":"street","parent":"610723"},{"adcode":"610723114","name":"华阳镇","level":"street","parent":"610723"},{"adcode":"610723115","name":"茅坪镇","level":"street","parent":"610723"},{"adcode":"610723119","name":"关帝镇","level":"street","parent":"610723"},{"adcode":"610723120","name":"桑溪镇","level":"street","parent":"610723"},{"adcode":"610723121","name":"八里关镇","level":"street","parent":"610723"}]