[{"adcode":"620722101","name":"洪水镇","level":"street","parent":"620722"},{"adcode":"620722102","name":"六坝镇","level":"street","parent":"620722"},{"adcode":"620722103","name":"新天镇","level":"street","parent":"620722"},{"adcode":"620722104","name":"南古镇","level":"street","parent":"620722"},{"adcode":"620722105","name":"永固镇","level":"street","parent":"620722"},{"adcode":"620722106","name":"三堡镇","level":"street","parent":"620722"},{"adcode":"620722107","name":"南丰镇","level":"street","parent":"620722"},{"adcode":"620722108","name":"民联镇","level":"street","parent":"620722"},{"adcode":"620722109","name":"顺化镇","level":"street","parent":"620722"},{"adcode":"620722110","name":"丰乐镇","level":"street","parent":"620722"}]