[{"adcode":"620725101","name":"清泉镇","level":"street","parent":"620725"},{"adcode":"620725102","name":"位奇镇","level":"street","parent":"620725"},{"adcode":"620725103","name":"霍城镇","level":"street","parent":"620725"},{"adcode":"620725104","name":"陈户镇","level":"street","parent":"620725"},{"adcode":"620725105","name":"大马营镇","level":"street","parent":"620725"},{"adcode":"620725106","name":"东乐镇","level":"street","parent":"620725"},{"adcode":"620725203","name":"老军乡","level":"street","parent":"620725"},{"adcode":"620725204","name":"李桥乡","level":"street","parent":"620725"},{"adcode":"620725400","name":"国营山丹农场","level":"street","parent":"620725"},{"adcode":"620725402","name":"中牧公司山丹马场","level":"street","parent":"620725"}]